whatsmynamejx1/name.py
whatsmynamejx1-1.0.0.dist-info/LICENSE
whatsmynamejx1-1.0.0.dist-info/METADATA
whatsmynamejx1-1.0.0.dist-info/WHEEL
whatsmynamejx1-1.0.0.dist-info/top_level.txt
whatsmynamejx1-1.0.0.dist-info/RECORD
